quiik/__init__.py
quiik/__main__.py
quiik/core.py
Quiik-2.0.1.dist-info/METADATA
Quiik-2.0.1.dist-info/WHEEL
Quiik-2.0.1.dist-info/entry_points.txt
Quiik-2.0.1.dist-info/top_level.txt
Quiik-2.0.1.dist-info/RECORD
